{
  "nav.dashboard": "Panel de control",
  "nav.events": "Eventos",
  "nav.group.compute": "Cómputo",
  "nav.group.network": "Red",
  "nav.group.storage": "Almacenamiento",
  "nav.group.administration": "Administración",
  "nav.vms": "Máquinas virtuales",
  "nav.vmsTemplates": "VMs y plantillas",
  "nav.templates": "Plantillas",
  "nav.pools": "Pools",
  "nav.instanceTypes": "Tipos de instancia",
  "nav.hosts": "Hosts",
  "nav.hostsClusters": "Hosts y clústeres",
  "nav.datacenters": "Centros de datos",
  "nav.clusters": "Clústeres",
  "nav.networks": "Redes",
  "nav.vnicProfiles": "Perfiles vNIC",
  "nav.storageDomains": "Dominios de almacenamiento",
  "nav.disks": "Discos",
  "nav.volumes": "Volúmenes",
  "nav.users": "Usuarios",
  "nav.quotas": "Cuotas",
  "nav.macPools": "Pools de direcciones MAC",
  "nav.providers": "Proveedores",
  "nav.errata": "Erratas",
  "nav.monitoringPortal": "Portal de supervisión",
  "monitoring.live.heading": "Utilización actual",
  "monitoring.history.heading": "Historial",
  "monitoring.history.empty": "Aún no hay datos de historial",
  "monitoring.checking": "Comprobando disponibilidad de supervisión",
  "monitoring.available.title": "Paneles históricos disponibles",
  "monitoring.available.body": "El historial completo de CPU, memoria, disco y red está disponible en el Portal de supervisión de oVirt (Grafana).",
  "monitoring.unavailable.title": "Historial de supervisión no disponible",
  "monitoring.unavailable.body": "Los paneles del Data Warehouse / Grafana no son accesibles. La utilización actual anterior sigue funcionando; los gráficos históricos requieren que el Data Warehouse esté instalado y accesible.",
  "monitoring.openPortal": "Abrir portal de supervisión",
  "monitoring.retry": "Reintentar",
  "masthead.globalNav": "Navegación global",
  "masthead.collapseNav": "Contraer navegación",
  "masthead.expandNav": "Expandir navegación",
  "masthead.toggleTheme": "Cambiar tema de color",
  "login.title": "Iniciar sesión en oVirt Console",
  "login.username": "Nombre de usuario",
  "login.password": "Contraseña",
  "login.usernamePlaceholder": "p. ej. admin@ovirt",
  "login.profile": "Perfil",
  "login.profileInternalsso": "internalsso (Keycloak SSO — oVirt 4.5+)",
  "login.profileInternal": "internal (aaa-jdbc heredado)",
  "login.profileOther": "Otro…",
  "login.profileCustom": "Nombre del perfil",
  "login.profileCustomPlaceholder": "p. ej. ldap-authz",
  "login.signingInAs": "Iniciando sesión como {principal}",
  "login.submit": "Iniciar sesión",
  "login.failed": "Error al iniciar sesión",
  "action.start": "Iniciar",
  "action.stop": "Detener",
  "action.reboot": "Reiniciar",
  "action.suspend": "Suspender",
  "action.remove": "Eliminar",
  "viewState.loading": "Cargando",
  "viewState.error": "Algo salió mal",
  "viewState.empty": "Aún no hay nada aquí",
  "viewState.populated": "Listo",
  "action.retry": "Reintentar"
}
